drf_scafolld/__init__.py
drf_scafolld/management/__init__.py
drf_scafolld/management/commands/__init__.py
drf_scafolld/management/commands/constants.py
drf_scafolld/management/commands/startdrfapp.py
drf_scafolld-0.1.1.dist-info/METADATA
drf_scafolld-0.1.1.dist-info/RECORD
drf_scafolld-0.1.1.dist-info/WHEEL
drf_scafolld-0.1.1.dist-info/top_level.txt
