Metadata-Version: 2.1
Name: drf-scafolld
Version: 0.1.1
Summary: Dead simple custom command to create a django app with djando rest framework CRUD RESTFull API
Home-page: https://github.com/juliosmelo/drf_scafolld
Author: juliocsmelo
Author-email: juliocsmelo@gmail.com
License: MIT
Platform: UNKNOWN
Classifier: Development Status :: 5 - Production/Stable
Classifier: Environment :: Web Environment
Classifier: Framework :: Django
Classifier: Intended Audience :: Developers
Classifier: License :: OSI Approved :: MIT License
Classifier: Natural Language :: English
Classifier: Operating System :: POSIX :: Linux
Classifier: Programming Language :: Python
Classifier: Programming Language :: Python :: 2
Classifier: Programming Language :: Python :: 2.7
Classifier: Programming Language :: Python :: 3
Classifier: Programming Language :: Python :: 3.4
Classifier: Programming Language :: Python :: 3.5
Classifier: Programming Language :: Python :: 3.6
Classifier: Topic :: System :: Installation/Setup
Requires-Dist: Django (>=1.11)
Requires-Dist: djangorestframework (>=3.8.2)
